celery_sqlalchemy_v2_scheduler/__init__.py
celery_sqlalchemy_v2_scheduler/models.py
celery_sqlalchemy_v2_scheduler/schedulers.py
celery_sqlalchemy_v2_scheduler/session.py
celery_sqlalchemy_v2_scheduler/tzcrontab.py
celery_sqlalchemy_v2_scheduler-0.1.2.dist-info/METADATA
celery_sqlalchemy_v2_scheduler-0.1.2.dist-info/WHEEL
celery_sqlalchemy_v2_scheduler-0.1.2.dist-info/licenses/LICENSE
celery_sqlalchemy_v2_scheduler-0.1.2.dist-info/RECORD
