Metadata-Version: 2.4
Name: celery-sqlalchemy-v2-scheduler
Version: 0.1.2
Summary: Celery beat scheduler using SQLAlchemy, patched for SQLAlchemy 2.x
License-Expression: MIT
License-File: LICENSE
Keywords: celery,scheduler,sqlalchemy,beat
Author: haiconmeo
Author-email: haiconmeo54@gmail.com
Requires-Python: >=3.6
Classifier: Development Status :: 3 - Alpha
Classifier: Intended Audience :: Developers
Classifier: Topic :: Software Development :: Libraries
Classifier: Programming Language :: Python :: 3
Classifier: Programming Language :: Python :: 3.6
Requires-Dist: celery (>=4.2)
Requires-Dist: pytz
Requires-Dist: sqlalchemy
